crspectra/__init__.py
crspectra/connect.py
crspectra/crspectra.db
crspectra/crspectra.py
crspectra/external.py
crspectra/py.typed
crspectra-1.1.1.dist-info/LICENSE
crspectra-1.1.1.dist-info/METADATA
crspectra-1.1.1.dist-info/WHEEL
crspectra-1.1.1.dist-info/RECORD
