Metadata-Version: 2.1
Name: crspectra
Version: 1.1.1
Summary: Database of published cosmic-ray energy spectra
Home-page: https://github.com/kkrings/crspectra
License: GPL-3.0-only
Author: Kai Krings
Author-email: kai.krings@posteo.de
Requires-Python: >=3.8.1,<4.0.0
Classifier: License :: OSI Approved :: GNU General Public License v3 (GPLv3)
Classifier: Programming Language :: Python :: 3
Classifier: Programming Language :: Python :: 3.9
Classifier: Programming Language :: Python :: 3.10
Classifier: Programming Language :: Python :: 3.11
Requires-Dist: numpy (>=1.24.0,<2.0.0)
Requires-Dist: requests (>=2.28.0,<3.0.0)
Project-URL: Repository, https://github.com/kkrings/crspectra
